Metadata-Version: 2.1
Name: pyCRAC
Version: 1.5.2
Summary: Python NextGen sequencing data processing software
Home-page: http://sandergranneman.bio.ed.ac.uk/Granneman_Lab/pyCRAC_software.html
Author: Sander Granneman
Author-email: sgrannem@staffmail.ed.ac.uk
Classifier: Development Status :: 5 - Production/Stable
Classifier: Environment :: Console
Classifier: Intended Audience :: Education
Classifier: Intended Audience :: Developers
Classifier: Intended Audience :: Science/Research
Classifier: License :: Freeware
Classifier: Operating System :: MacOS :: MacOS X
Classifier: Operating System :: POSIX
Classifier: Programming Language :: Python :: 3.6
Classifier: Topic :: Scientific/Engineering :: Bio-Informatics
Classifier: Topic :: Software Development :: Libraries :: Application Frameworks
License-File: LICENSE
